README.rst
setup.py
src/fc_oogmsh/Matplotlib.py
src/fc_oogmsh/Mayavi.py
src/fc_oogmsh/Sys.py
src/fc_oogmsh/__init__.py
src/fc_oogmsh/demos.py
src/fc_oogmsh/gmsh.py
src/fc_oogmsh/msh.py
src/fc_oogmsh/msh4_0.py
src/fc_oogmsh/msh4_1.py
src/fc_oogmsh/oogmsh2.py
src/fc_oogmsh/oogmsh4.py
src/fc_oogmsh.egg-info/PKG-INFO
src/fc_oogmsh.egg-info/SOURCES.txt
src/fc_oogmsh.egg-info/dependency_links.txt
src/fc_oogmsh.egg-info/requires.txt
src/fc_oogmsh.egg-info/top_level.txt
src/fc_oogmsh/geodir/2d/barwith4holes.geo
src/fc_oogmsh/geodir/2d/condenser.geo
src/fc_oogmsh/geodir/2d/condenser10.geo
src/fc_oogmsh/geodir/2d/condenser11.geo
src/fc_oogmsh/geodir/2d/disk3holes.geo
src/fc_oogmsh/geodir/2d/disk5holes.geo
src/fc_oogmsh/geodir/2d/diskwith9holes.geo
src/fc_oogmsh/geodir/2d/magnetism.geo
src/fc_oogmsh/geodir/2d/options01_data.geo
src/fc_oogmsh/geodir/2d/partitions01_data.geo
src/fc_oogmsh/geodir/2d/partitions_shape.geo
src/fc_oogmsh/geodir/2d/rectanglepart.geo
src/fc_oogmsh/geodir/2d/sample20.geo
src/fc_oogmsh/geodir/2d/shape_functions.geo
src/fc_oogmsh/geodir/2d/square4.geo
src/fc_oogmsh/geodir/2d/square4dom.geo
src/fc_oogmsh/geodir/3d/ball8.geo
src/fc_oogmsh/geodir/3d/cube6.geo
src/fc_oogmsh/geodir/3d/cylinder3dom.geo
src/fc_oogmsh/geodir/3d/cylinder3holes.geo
src/fc_oogmsh/geodir/3d/cylinderkey.geo
src/fc_oogmsh/geodir/3d/demi_sphere1.geo
src/fc_oogmsh/geodir/3d/demi_sphere4.geo
src/fc_oogmsh/geodir/3d/options01_data.geo
src/fc_oogmsh/geodir/3d/quart_sphere2.geo
src/fc_oogmsh/geodir/3ds/demisphere4surf.geo
src/fc_oogmsh/geodir/3ds/demisphere5.geo
src/fc_oogmsh/geodir/3ds/sphere8surf.geo