Metadata-Version: 2.1
Name: fc-oogmsh
Version: 0.1.0
Summary: Generate and read mesh files by using gmsh and given .geo files
Home-page: http://www.math.univ-paris13.fr/~cuvelier/software
Author: Francois Cuvelier
Author-email: cuvelier@math.univ-paris13.fr
License: BSD
Platform: Linux
Platform: Mac OS-X
Platform: Windows
Classifier: Topic :: Scientific/Engineering
Provides-Extra: matplotlib4mesh
Provides-Extra: mayavi4mesh
